{
  "batchNumber": 36,
  "batchId": "ml-create-036",
  "strategy": "safe_small_batch",
  "executionHints": {
    "delayMs": 1500,
    "listingType": "gold_pro",
    "useSchemaBasePrice": true,
    "applyPricingStrategyAtRuntime": true,
    "stopIfFailureRateOver": 0.5
  },
  "items": [
    {
      "produtoId": "8d7f5b61-db52-419f-b4c3-2f35e1779729",
      "sku": "VTK013713",
      "nome": "Terminal Direção Dir Audi A1 Voyage Fox Gol Polo Saveiro",
      "fornecedor": "SHOPPECAS",
      "dsliteFornecedorId": "103",
      "custo": 31.21,
      "estoque": 100,
      "mlFee": 0.15,
      "mlShipping": 0,
      "customPrice": null,
      "suggestedPricePreview": 63.22,
      "priceSource": "pricing_strategy_preview",
      "pricingStrategy": {
        "margin": 0.15,
        "minProfit": 20
      },
      "strategyNotes": "Na execução, usar schema/base_price do sistema para recalcular taxa ML real e respeitar custom_price quando existir."
    },
    {
      "produtoId": "66e40323-bbf1-4ad3-a710-e59552c4cdff",
      "sku": "VTK013714",
      "nome": "Terminal Direção Lado Esquerdo Audi A1 Após 10",
      "fornecedor": "SHOPPECAS",
      "dsliteFornecedorId": "103",
      "custo": 31.21,
      "estoque": 100,
      "mlFee": 0.15,
      "mlShipping": 0,
      "customPrice": null,
      "suggestedPricePreview": 63.22,
      "priceSource": "pricing_strategy_preview",
      "pricingStrategy": {
        "margin": 0.15,
        "minProfit": 20
      },
      "strategyNotes": "Na execução, usar schema/base_price do sistema para recalcular taxa ML real e respeitar custom_price quando existir."
    },
    {
      "produtoId": "69ba56ba-8772-4682-82f1-5d6d323a4796",
      "sku": "VTK010928",
      "nome": "Tirante Tp Bag 206/207/306/307",
      "fornecedor": "SHOPPECAS",
      "dsliteFornecedorId": "103",
      "custo": 31.22,
      "estoque": 100,
      "mlFee": 0.15,
      "mlShipping": 0,
      "customPrice": 63.23,
      "suggestedPricePreview": 63.23,
      "priceSource": "custom_price",
      "pricingStrategy": {
        "margin": 0.15,
        "minProfit": 20
      },
      "strategyNotes": "Na execução, usar schema/base_price do sistema para recalcular taxa ML real e respeitar custom_price quando existir."
    },
    {
      "produtoId": "f5828623-f4ae-4eae-97b3-e390f28738d6",
      "sku": "VTK011150",
      "nome": "Trinco Quebra-vento Ld Kombi Clipper Preto",
      "fornecedor": "SHOPPECAS",
      "dsliteFornecedorId": "103",
      "custo": 31.26,
      "estoque": 100,
      "mlFee": 0.15,
      "mlShipping": 0,
      "customPrice": null,
      "suggestedPricePreview": 63.28,
      "priceSource": "pricing_strategy_preview",
      "pricingStrategy": {
        "margin": 0.15,
        "minProfit": 20
      },
      "strategyNotes": "Na execução, usar schema/base_price do sistema para recalcular taxa ML real e respeitar custom_price quando existir."
    },
    {
      "produtoId": "86df12a6-f436-453b-b47c-f32859d8c820",
      "sku": "VTK013110",
      "nome": "Cilindro Porta Direita Megane 97 A 05",
      "fornecedor": "SHOPPECAS",
      "dsliteFornecedorId": "103",
      "custo": 31.26,
      "estoque": 100,
      "mlFee": 0.15,
      "mlShipping": 0,
      "customPrice": null,
      "suggestedPricePreview": 63.28,
      "priceSource": "pricing_strategy_preview",
      "pricingStrategy": {
        "margin": 0.15,
        "minProfit": 20
      },
      "strategyNotes": "Na execução, usar schema/base_price do sistema para recalcular taxa ML real e respeitar custom_price quando existir."
    },
    {
      "produtoId": "cfc13cd3-efbb-4cda-98ea-38f0878ea160",
      "sku": "VTK013111",
      "nome": "Cilindro Porta Esquerda Megane 97 A 05",
      "fornecedor": "SHOPPECAS",
      "dsliteFornecedorId": "103",
      "custo": 31.26,
      "estoque": 100,
      "mlFee": 0.15,
      "mlShipping": 0,
      "customPrice": null,
      "suggestedPricePreview": 63.28,
      "priceSource": "pricing_strategy_preview",
      "pricingStrategy": {
        "margin": 0.15,
        "minProfit": 20
      },
      "strategyNotes": "Na execução, usar schema/base_price do sistema para recalcular taxa ML real e respeitar custom_price quando existir."
    },
    {
      "produtoId": "223ca687-b5f4-4c12-b287-da6ea7f5f828",
      "sku": "VTK013225",
      "nome": "Cab Aco Limit Tp Cacamb C370mm Ranger Ap13 D/e",
      "fornecedor": "SHOPPECAS",
      "dsliteFornecedorId": "103",
      "custo": 31.29,
      "estoque": 100,
      "mlFee": 0.15,
      "mlShipping": 0,
      "customPrice": null,
      "suggestedPricePreview": 63.32,
      "priceSource": "pricing_strategy_preview",
      "pricingStrategy": {
        "margin": 0.15,
        "minProfit": 20
      },
      "strategyNotes": "Na execução, usar schema/base_price do sistema para recalcular taxa ML real e respeitar custom_price quando existir."
    },
    {
      "produtoId": "ddaab404-5416-4bae-911a-df70e5a4b36e",
      "sku": "VTK013746",
      "nome": "Terminal Direção Lado Direito Ou Esquerdo Celta Após 01",
      "fornecedor": "SHOPPECAS",
      "dsliteFornecedorId": "103",
      "custo": 31.29,
      "estoque": 100,
      "mlFee": 0.15,
      "mlShipping": 0,
      "customPrice": null,
      "suggestedPricePreview": 63.32,
      "priceSource": "pricing_strategy_preview",
      "pricingStrategy": {
        "margin": 0.15,
        "minProfit": 20
      },
      "strategyNotes": "Na execução, usar schema/base_price do sistema para recalcular taxa ML real e respeitar custom_price quando existir."
    },
    {
      "produtoId": "32263f96-c19b-471c-a4e7-e94c0100d588",
      "sku": "VTK011129",
      "nome": "Porca Fecho P Mala Gol/pas/voyage",
      "fornecedor": "SHOPPECAS",
      "dsliteFornecedorId": "103",
      "custo": 31.3,
      "estoque": 100,
      "mlFee": 0.15,
      "mlShipping": 0,
      "customPrice": null,
      "suggestedPricePreview": 63.33,
      "priceSource": "pricing_strategy_preview",
      "pricingStrategy": {
        "margin": 0.15,
        "minProfit": 20
      },
      "strategyNotes": "Na execução, usar schema/base_price do sistema para recalcular taxa ML real e respeitar custom_price quando existir."
    },
    {
      "produtoId": "6309903e-e566-4c9b-a0cf-32a32c86ae3d",
      "sku": "VTK011901",
      "nome": "Calco Mac Ext Da Porta Vw Constellation Dir",
      "fornecedor": "SHOPPECAS",
      "dsliteFornecedorId": "103",
      "custo": 31.3,
      "estoque": 100,
      "mlFee": 0.15,
      "mlShipping": 0,
      "customPrice": null,
      "suggestedPricePreview": 63.33,
      "priceSource": "pricing_strategy_preview",
      "pricingStrategy": {
        "margin": 0.15,
        "minProfit": 20
      },
      "strategyNotes": "Na execução, usar schema/base_price do sistema para recalcular taxa ML real e respeitar custom_price quando existir."
    },
    {
      "produtoId": "ca255e88-e66d-4c23-b0ab-855f65c2b286",
      "sku": "VTK011902",
      "nome": "Calco Mac Ext Da Porta Vw Constellation Esq",
      "fornecedor": "SHOPPECAS",
      "dsliteFornecedorId": "103",
      "custo": 31.3,
      "estoque": 100,
      "mlFee": 0.15,
      "mlShipping": 0,
      "customPrice": null,
      "suggestedPricePreview": 63.33,
      "priceSource": "pricing_strategy_preview",
      "pricingStrategy": {
        "margin": 0.15,
        "minProfit": 20
      },
      "strategyNotes": "Na execução, usar schema/base_price do sistema para recalcular taxa ML real e respeitar custom_price quando existir."
    },
    {
      "produtoId": "33d7380c-af5f-4344-bae1-941cbac2257e",
      "sku": "VTK013120",
      "nome": "Maçaneta Externa Abert Capô Fusca 1200 Até 71",
      "fornecedor": "SHOPPECAS",
      "dsliteFornecedorId": "103",
      "custo": 31.46,
      "estoque": 100,
      "mlFee": 0.15,
      "mlShipping": 0,
      "customPrice": 63.53,
      "suggestedPricePreview": 63.53,
      "priceSource": "custom_price",
      "pricingStrategy": {
        "margin": 0.15,
        "minProfit": 20
      },
      "strategyNotes": "Na execução, usar schema/base_price do sistema para recalcular taxa ML real e respeitar custom_price quando existir."
    },
    {
      "produtoId": "1e9f89d2-cbd7-418b-98f8-f6b34a43c33d",
      "sku": "VTK012547",
      "nome": "Breu Vr300 Escuro D Addario",
      "fornecedor": "BKR1",
      "dsliteFornecedorId": "108",
      "custo": 31.49,
      "estoque": 7,
      "mlFee": 0.15,
      "mlShipping": 0,
      "customPrice": null,
      "suggestedPricePreview": 63.57,
      "priceSource": "pricing_strategy_preview",
      "pricingStrategy": {
        "margin": 0.15,
        "minProfit": 20
      },
      "strategyNotes": "Na execução, usar schema/base_price do sistema para recalcular taxa ML real e respeitar custom_price quando existir."
    },
    {
      "produtoId": "f4a0119d-e227-466a-911c-622b7a172adc",
      "sku": "VTK012611",
      "nome": "Breu Vr200 Claro D Addario",
      "fornecedor": "BKR1",
      "dsliteFornecedorId": "108",
      "custo": 31.49,
      "estoque": 5,
      "mlFee": 0.15,
      "mlShipping": 0,
      "customPrice": null,
      "suggestedPricePreview": 63.57,
      "priceSource": "pricing_strategy_preview",
      "pricingStrategy": {
        "margin": 0.15,
        "minProfit": 20
      },
      "strategyNotes": "Na execução, usar schema/base_price do sistema para recalcular taxa ML real e respeitar custom_price quando existir."
    },
    {
      "produtoId": "fedf3572-c213-4727-9cba-5605772d78db",
      "sku": "VTK013815",
      "nome": "Terminal Direção Lado Direito Linea G1 Fase 1 Punto G1",
      "fornecedor": "SHOPPECAS",
      "dsliteFornecedorId": "103",
      "custo": 31.5,
      "estoque": 100,
      "mlFee": 0.15,
      "mlShipping": 0,
      "customPrice": null,
      "suggestedPricePreview": 63.58,
      "priceSource": "pricing_strategy_preview",
      "pricingStrategy": {
        "margin": 0.15,
        "minProfit": 20
      },
      "strategyNotes": "Na execução, usar schema/base_price do sistema para recalcular taxa ML real e respeitar custom_price quando existir."
    },
    {
      "produtoId": "286ea187-2cb5-42cf-b887-0508e7d06732",
      "sku": "VTK013821",
      "nome": "Bieleta Dianteira Esquerda Direita Vectra Zafira Corsa G2",
      "fornecedor": "SHOPPECAS",
      "dsliteFornecedorId": "103",
      "custo": 31.52,
      "estoque": 100,
      "mlFee": 0.15,
      "mlShipping": 0,
      "customPrice": null,
      "suggestedPricePreview": 63.6,
      "priceSource": "pricing_strategy_preview",
      "pricingStrategy": {
        "margin": 0.15,
        "minProfit": 20
      },
      "strategyNotes": "Na execução, usar schema/base_price do sistema para recalcular taxa ML real e respeitar custom_price quando existir."
    },
    {
      "produtoId": "a153cac8-45b6-4326-9044-4830ad6817f3",
      "sku": "VTK013480",
      "nome": "Chave S/segr Pf Convencional Ford F-1000 79a98",
      "fornecedor": "SHOPPECAS",
      "dsliteFornecedorId": "103",
      "custo": 31.61,
      "estoque": 100,
      "mlFee": 0.15,
      "mlShipping": 0,
      "customPrice": null,
      "suggestedPricePreview": 63.72,
      "priceSource": "pricing_strategy_preview",
      "pricingStrategy": {
        "margin": 0.15,
        "minProfit": 20
      },
      "strategyNotes": "Na execução, usar schema/base_price do sistema para recalcular taxa ML real e respeitar custom_price quando existir."
    },
    {
      "produtoId": "c66822a4-84b3-4ac7-a719-21aee22c80fc",
      "sku": "VTK013481",
      "nome": "Chave S/segr Perfil Conven Ford Del Rey 81a91",
      "fornecedor": "SHOPPECAS",
      "dsliteFornecedorId": "103",
      "custo": 31.61,
      "estoque": 100,
      "mlFee": 0.15,
      "mlShipping": 0,
      "customPrice": null,
      "suggestedPricePreview": 63.72,
      "priceSource": "pricing_strategy_preview",
      "pricingStrategy": {
        "margin": 0.15,
        "minProfit": 20
      },
      "strategyNotes": "Na execução, usar schema/base_price do sistema para recalcular taxa ML real e respeitar custom_price quando existir."
    },
    {
      "produtoId": "947fab29-3196-4269-805a-eeee9d87615f",
      "sku": "VTK013482",
      "nome": "Chave S/segr Convencional Ford Escort 83 A 92",
      "fornecedor": "SHOPPECAS",
      "dsliteFornecedorId": "103",
      "custo": 31.61,
      "estoque": 100,
      "mlFee": 0.15,
      "mlShipping": 0,
      "customPrice": null,
      "suggestedPricePreview": 63.72,
      "priceSource": "pricing_strategy_preview",
      "pricingStrategy": {
        "margin": 0.15,
        "minProfit": 20
      },
      "strategyNotes": "Na execução, usar schema/base_price do sistema para recalcular taxa ML real e respeitar custom_price quando existir."
    },
    {
      "produtoId": "b3b172a6-cf7d-4645-9ea3-038875970922",
      "sku": "VTK011154",
      "nome": "Kit Batente Porta Dianteira Dir Esq Kombi 57 A 75 5 Pçs",
      "fornecedor": "SHOPPECAS",
      "dsliteFornecedorId": "103",
      "custo": 31.64,
      "estoque": 96,
      "mlFee": 0.15,
      "mlShipping": 0,
      "customPrice": null,
      "suggestedPricePreview": 63.75,
      "priceSource": "pricing_strategy_preview",
      "pricingStrategy": {
        "margin": 0.15,
        "minProfit": 20
      },
      "strategyNotes": "Na execução, usar schema/base_price do sistema para recalcular taxa ML real e respeitar custom_price quando existir."
    },
    {
      "produtoId": "3b279584-d502-4cb6-bb6f-893ed8933d14",
      "sku": "VTK011350",
      "nome": "Manivela Reguladora Do Vidro Porta Dianteira Direita E Esquerda Cinza Nylon - Volkswagen Gol Gii 94 à 01 - Parati Gii 96",
      "fornecedor": "SHOPPECAS",
      "dsliteFornecedorId": "103",
      "custo": 31.68,
      "estoque": 100,
      "mlFee": 0.15,
      "mlShipping": 0,
      "customPrice": null,
      "suggestedPricePreview": 63.8,
      "priceSource": "pricing_strategy_preview",
      "pricingStrategy": {
        "margin": 0.15,
        "minProfit": 20
      },
      "strategyNotes": "Na execução, usar schema/base_price do sistema para recalcular taxa ML real e respeitar custom_price quando existir."
    },
    {
      "produtoId": "5a5ed20b-a46b-4bbe-bf07-89b991aa5a30",
      "sku": "VTK013308",
      "nome": "Par Batente Porta-malas Escort E Escort Hobby 1983-1996",
      "fornecedor": "SHOPPECAS",
      "dsliteFornecedorId": "103",
      "custo": 31.75,
      "estoque": 100,
      "mlFee": 0.15,
      "mlShipping": 0,
      "customPrice": null,
      "suggestedPricePreview": 63.89,
      "priceSource": "pricing_strategy_preview",
      "pricingStrategy": {
        "margin": 0.15,
        "minProfit": 20
      },
      "strategyNotes": "Na execução, usar schema/base_price do sistema para recalcular taxa ML real e respeitar custom_price quando existir."
    },
    {
      "produtoId": "95a9e760-7a91-4b3a-ad7e-8dd0828024b2",
      "sku": "VTK010970",
      "nome": "Chave Com Alojamento Frontier Livina Tiida Hatch E Sedan",
      "fornecedor": "SHOPPECAS",
      "dsliteFornecedorId": "103",
      "custo": 31.83,
      "estoque": 100,
      "mlFee": 0.15,
      "mlShipping": 0,
      "customPrice": null,
      "suggestedPricePreview": 63.99,
      "priceSource": "pricing_strategy_preview",
      "pricingStrategy": {
        "margin": 0.15,
        "minProfit": 20
      },
      "strategyNotes": "Na execução, usar schema/base_price do sistema para recalcular taxa ML real e respeitar custom_price quando existir."
    },
    {
      "produtoId": "973d8b7f-f397-409f-a4bd-a6a4454a5e01",
      "sku": "VTK011452",
      "nome": "Gatilho Maçaneta Interna Porta Direita Preta Gol Quadrado",
      "fornecedor": "SHOPPECAS",
      "dsliteFornecedorId": "103",
      "custo": 31.95,
      "estoque": 100,
      "mlFee": 0.15,
      "mlShipping": 0,
      "customPrice": null,
      "suggestedPricePreview": 64.14,
      "priceSource": "pricing_strategy_preview",
      "pricingStrategy": {
        "margin": 0.15,
        "minProfit": 20
      },
      "strategyNotes": "Na execução, usar schema/base_price do sistema para recalcular taxa ML real e respeitar custom_price quando existir."
    },
    {
      "produtoId": "14887675-e13f-4a31-916c-37dc8ea2b4d8",
      "sku": "VTK011453",
      "nome": "Maçaneta Int Porta Esq Parati Santana Voyage Plástico Preta",
      "fornecedor": "SHOPPECAS",
      "dsliteFornecedorId": "103",
      "custo": 31.95,
      "estoque": 100,
      "mlFee": 0.15,
      "mlShipping": 0,
      "customPrice": null,
      "suggestedPricePreview": 64.14,
      "priceSource": "pricing_strategy_preview",
      "pricingStrategy": {
        "margin": 0.15,
        "minProfit": 20
      },
      "strategyNotes": "Na execução, usar schema/base_price do sistema para recalcular taxa ML real e respeitar custom_price quando existir."
    }
  ]
}