{
  "batchNumber": 49,
  "batchId": "ml-create-049",
  "strategy": "safe_small_batch",
  "executionHints": {
    "delayMs": 1500,
    "listingType": "gold_pro",
    "useSchemaBasePrice": true,
    "applyPricingStrategyAtRuntime": true,
    "stopIfFailureRateOver": 0.5
  },
  "items": [
    {
      "produtoId": "6d3b4d31-56e9-4e65-b845-7b34605f5e28",
      "sku": "VTK013631",
      "nome": "Maçaneta Tampa Caçamba Ranger 98 A 04 Plástica (cromada)",
      "fornecedor": "SHOPPECAS",
      "dsliteFornecedorId": "103",
      "custo": 45.47,
      "estoque": 100,
      "mlFee": 0.15,
      "mlShipping": 0,
      "customPrice": null,
      "suggestedPricePreview": 80.83,
      "priceSource": "pricing_strategy_preview",
      "pricingStrategy": {
        "margin": 0.15,
        "minProfit": 20
      },
      "strategyNotes": "Na execução, usar schema/base_price do sistema para recalcular taxa ML real e respeitar custom_price quando existir."
    },
    {
      "produtoId": "a3add9a2-6e8a-4407-9d26-5f38edab42c3",
      "sku": "VTK013645",
      "nome": "Arm Inf Pta Trav Guia Carg D/e",
      "fornecedor": "SHOPPECAS",
      "dsliteFornecedorId": "103",
      "custo": 45.68,
      "estoque": 100,
      "mlFee": 0.15,
      "mlShipping": 0,
      "customPrice": null,
      "suggestedPricePreview": 81.09,
      "priceSource": "pricing_strategy_preview",
      "pricingStrategy": {
        "margin": 0.15,
        "minProfit": 20
      },
      "strategyNotes": "Na execução, usar schema/base_price do sistema para recalcular taxa ML real e respeitar custom_price quando existir."
    },
    {
      "produtoId": "19b0f720-9c53-4f32-8512-d54e70133397",
      "sku": "VTK013843",
      "nome": "Bieleta Dianteira Esquerda Direita Transit Após 13",
      "fornecedor": "SHOPPECAS",
      "dsliteFornecedorId": "103",
      "custo": 45.71,
      "estoque": 100,
      "mlFee": 0.15,
      "mlShipping": 0,
      "customPrice": null,
      "suggestedPricePreview": 81.12,
      "priceSource": "pricing_strategy_preview",
      "pricingStrategy": {
        "margin": 0.15,
        "minProfit": 20
      },
      "strategyNotes": "Na execução, usar schema/base_price do sistema para recalcular taxa ML real e respeitar custom_price quando existir."
    },
    {
      "produtoId": "b098a988-1fc2-41dc-bc2b-869fdeb44cac",
      "sku": "VTK010962",
      "nome": "Maçaneta Interna Porta Esq Diant Tras Pajero Sport L200",
      "fornecedor": "SHOPPECAS",
      "dsliteFornecedorId": "103",
      "custo": 45.78,
      "estoque": 97,
      "mlFee": 0.15,
      "mlShipping": 0,
      "customPrice": null,
      "suggestedPricePreview": 81.21,
      "priceSource": "pricing_strategy_preview",
      "pricingStrategy": {
        "margin": 0.15,
        "minProfit": 20
      },
      "strategyNotes": "Na execução, usar schema/base_price do sistema para recalcular taxa ML real e respeitar custom_price quando existir."
    },
    {
      "produtoId": "765c08d2-adea-434a-b268-c9a0225e1c64",
      "sku": "VTK013583",
      "nome": "Limitador Porta Traseira (baú) Esq Ford Furgão Longo Após 09",
      "fornecedor": "SHOPPECAS",
      "dsliteFornecedorId": "103",
      "custo": 45.85,
      "estoque": 100,
      "mlFee": 0.15,
      "mlShipping": 0,
      "customPrice": null,
      "suggestedPricePreview": 81.3,
      "priceSource": "pricing_strategy_preview",
      "pricingStrategy": {
        "margin": 0.15,
        "minProfit": 20
      },
      "strategyNotes": "Na execução, usar schema/base_price do sistema para recalcular taxa ML real e respeitar custom_price quando existir."
    },
    {
      "produtoId": "ce303442-7de7-4e53-8b33-2657193072b3",
      "sku": "VTK013584",
      "nome": "Limitador Porta Traseira (baú) Dir Ford Furgão Longo Após 09",
      "fornecedor": "SHOPPECAS",
      "dsliteFornecedorId": "103",
      "custo": 45.85,
      "estoque": 100,
      "mlFee": 0.15,
      "mlShipping": 0,
      "customPrice": null,
      "suggestedPricePreview": 81.3,
      "priceSource": "pricing_strategy_preview",
      "pricingStrategy": {
        "margin": 0.15,
        "minProfit": 20
      },
      "strategyNotes": "Na execução, usar schema/base_price do sistema para recalcular taxa ML real e respeitar custom_price quando existir."
    },
    {
      "produtoId": "2cc9f9e6-30ff-4d6d-a375-bd5c890a1c65",
      "sku": "VTK011228",
      "nome": "Limitador Porta Dianteira Direita/esquerda Agrale G3 Após 12",
      "fornecedor": "SHOPPECAS",
      "dsliteFornecedorId": "103",
      "custo": 45.96,
      "estoque": 100,
      "mlFee": 0.15,
      "mlShipping": 0,
      "customPrice": null,
      "suggestedPricePreview": 81.43,
      "priceSource": "pricing_strategy_preview",
      "pricingStrategy": {
        "margin": 0.15,
        "minProfit": 20
      },
      "strategyNotes": "Na execução, usar schema/base_price do sistema para recalcular taxa ML real e respeitar custom_price quando existir."
    },
    {
      "produtoId": "6af54c71-ef5d-4e1c-9f02-40556d0a753f",
      "sku": "VTK011229",
      "nome": "Limitador Porta Dianteira Direita Esquerda Santana Quantum",
      "fornecedor": "SHOPPECAS",
      "dsliteFornecedorId": "103",
      "custo": 45.96,
      "estoque": 100,
      "mlFee": 0.15,
      "mlShipping": 0,
      "customPrice": null,
      "suggestedPricePreview": 81.43,
      "priceSource": "pricing_strategy_preview",
      "pricingStrategy": {
        "margin": 0.15,
        "minProfit": 20
      },
      "strategyNotes": "Na execução, usar schema/base_price do sistema para recalcular taxa ML real e respeitar custom_price quando existir."
    },
    {
      "produtoId": "19d2fee4-5406-40c5-9d2b-efb13b2bfe71",
      "sku": "VTK010506",
      "nome": "Comutador Ignicao Renault Megane Hatch 97a05",
      "fornecedor": "SHOPPECAS",
      "dsliteFornecedorId": "103",
      "custo": 46.22,
      "estoque": 100,
      "mlFee": 0.15,
      "mlShipping": 0,
      "customPrice": null,
      "suggestedPricePreview": 81.75,
      "priceSource": "pricing_strategy_preview",
      "pricingStrategy": {
        "margin": 0.15,
        "minProfit": 20
      },
      "strategyNotes": "Na execução, usar schema/base_price do sistema para recalcular taxa ML real e respeitar custom_price quando existir."
    },
    {
      "produtoId": "404c940c-5e6d-4937-8813-7b11ab55ee41",
      "sku": "VTK011449",
      "nome": "Maçaneta Interna Porta Esq Gol Parati G2 Metal Cromada",
      "fornecedor": "SHOPPECAS",
      "dsliteFornecedorId": "103",
      "custo": 46.27,
      "estoque": 100,
      "mlFee": 0.15,
      "mlShipping": 0,
      "customPrice": null,
      "suggestedPricePreview": 81.81,
      "priceSource": "pricing_strategy_preview",
      "pricingStrategy": {
        "margin": 0.15,
        "minProfit": 20
      },
      "strategyNotes": "Na execução, usar schema/base_price do sistema para recalcular taxa ML real e respeitar custom_price quando existir."
    },
    {
      "produtoId": "4f7abb83-590c-4ab0-a611-445439124bda",
      "sku": "VTK013187",
      "nome": "Maçaneta Externa Dianteira Direita Metal Gol Parati 80 à 86",
      "fornecedor": "SHOPPECAS",
      "dsliteFornecedorId": "103",
      "custo": 46.29,
      "estoque": 100,
      "mlFee": 0.15,
      "mlShipping": 0,
      "customPrice": null,
      "suggestedPricePreview": 81.84,
      "priceSource": "pricing_strategy_preview",
      "pricingStrategy": {
        "margin": 0.15,
        "minProfit": 20
      },
      "strategyNotes": "Na execução, usar schema/base_price do sistema para recalcular taxa ML real e respeitar custom_price quando existir."
    },
    {
      "produtoId": "f8ea9a6d-743d-46ad-bb71-b625ab7a1c64",
      "sku": "VTK013188",
      "nome": "Maçaneta Externa Dianteira Esquerda Metal Gol Parati 80 à 86",
      "fornecedor": "SHOPPECAS",
      "dsliteFornecedorId": "103",
      "custo": 46.29,
      "estoque": 100,
      "mlFee": 0.15,
      "mlShipping": 0,
      "customPrice": null,
      "suggestedPricePreview": 81.84,
      "priceSource": "pricing_strategy_preview",
      "pricingStrategy": {
        "margin": 0.15,
        "minProfit": 20
      },
      "strategyNotes": "Na execução, usar schema/base_price do sistema para recalcular taxa ML real e respeitar custom_price quando existir."
    },
    {
      "produtoId": "2a8da775-6a7f-4922-9257-8681cf0d71d4",
      "sku": "VTK013192",
      "nome": "Maçaneta Externa Dianteira Direita Metal Gol 1987 Até 1996",
      "fornecedor": "SHOPPECAS",
      "dsliteFornecedorId": "103",
      "custo": 46.29,
      "estoque": 100,
      "mlFee": 0.15,
      "mlShipping": 0,
      "customPrice": null,
      "suggestedPricePreview": 81.84,
      "priceSource": "pricing_strategy_preview",
      "pricingStrategy": {
        "margin": 0.15,
        "minProfit": 20
      },
      "strategyNotes": "Na execução, usar schema/base_price do sistema para recalcular taxa ML real e respeitar custom_price quando existir."
    },
    {
      "produtoId": "192551b3-132c-430a-86c7-ce2f5aff78b7",
      "sku": "VTK013193",
      "nome": "Maçaneta Externa Dianteira Esquerda Metal Gol 1987 Até 1996",
      "fornecedor": "SHOPPECAS",
      "dsliteFornecedorId": "103",
      "custo": 46.29,
      "estoque": 100,
      "mlFee": 0.15,
      "mlShipping": 0,
      "customPrice": null,
      "suggestedPricePreview": 81.84,
      "priceSource": "pricing_strategy_preview",
      "pricingStrategy": {
        "margin": 0.15,
        "minProfit": 20
      },
      "strategyNotes": "Na execução, usar schema/base_price do sistema para recalcular taxa ML real e respeitar custom_price quando existir."
    },
    {
      "produtoId": "3117ec67-12f2-4056-8805-e6867d0d7305",
      "sku": "VTK013531",
      "nome": "Manivela Regulagem Vidro Ford Caminhões Corcel Belina",
      "fornecedor": "SHOPPECAS",
      "dsliteFornecedorId": "103",
      "custo": 46.39,
      "estoque": 100,
      "mlFee": 0.15,
      "mlShipping": 0,
      "customPrice": null,
      "suggestedPricePreview": 81.96,
      "priceSource": "pricing_strategy_preview",
      "pricingStrategy": {
        "margin": 0.15,
        "minProfit": 20
      },
      "strategyNotes": "Na execução, usar schema/base_price do sistema para recalcular taxa ML real e respeitar custom_price quando existir."
    },
    {
      "produtoId": "b5b488b9-e554-4193-a436-443cc6ca5d7d",
      "sku": "VTK011638",
      "nome": "Maçaneta Externa Porta Dir Crom Gol Parati Quantum Saveiro",
      "fornecedor": "SHOPPECAS",
      "dsliteFornecedorId": "103",
      "custo": 46.51,
      "estoque": 100,
      "mlFee": 0.15,
      "mlShipping": 0,
      "customPrice": null,
      "suggestedPricePreview": 82.11,
      "priceSource": "pricing_strategy_preview",
      "pricingStrategy": {
        "margin": 0.15,
        "minProfit": 20
      },
      "strategyNotes": "Na execução, usar schema/base_price do sistema para recalcular taxa ML real e respeitar custom_price quando existir."
    },
    {
      "produtoId": "76d8e7b9-d866-476a-871a-14d8803ae326",
      "sku": "VTK013309",
      "nome": "Fechadura Superior Porta-malas Belina 2",
      "fornecedor": "SHOPPECAS",
      "dsliteFornecedorId": "103",
      "custo": 46.51,
      "estoque": 100,
      "mlFee": 0.15,
      "mlShipping": 0,
      "customPrice": null,
      "suggestedPricePreview": 82.11,
      "priceSource": "pricing_strategy_preview",
      "pricingStrategy": {
        "margin": 0.15,
        "minProfit": 20
      },
      "strategyNotes": "Na execução, usar schema/base_price do sistema para recalcular taxa ML real e respeitar custom_price quando existir."
    },
    {
      "produtoId": "8b548997-3985-4295-b7bd-70e3cc457c79",
      "sku": "VTK011628",
      "nome": "Maçaneta Externa Porta  Diant Gol Parati G2  Saveiro Preta",
      "fornecedor": "SHOPPECAS",
      "dsliteFornecedorId": "103",
      "custo": 46.53,
      "estoque": 100,
      "mlFee": 0.15,
      "mlShipping": 0,
      "customPrice": null,
      "suggestedPricePreview": 82.14,
      "priceSource": "pricing_strategy_preview",
      "pricingStrategy": {
        "margin": 0.15,
        "minProfit": 20
      },
      "strategyNotes": "Na execução, usar schema/base_price do sistema para recalcular taxa ML real e respeitar custom_price quando existir."
    },
    {
      "produtoId": "4a08692c-bdbf-4564-ba11-4cadd3e88d9b",
      "sku": "VTK013751",
      "nome": "Terminal Direção 225mm Lado Esquerdo Hilux Sw4 Gi 95 A 01",
      "fornecedor": "SHOPPECAS",
      "dsliteFornecedorId": "103",
      "custo": 46.61,
      "estoque": 100,
      "mlFee": 0.15,
      "mlShipping": 0,
      "customPrice": null,
      "suggestedPricePreview": 82.23,
      "priceSource": "pricing_strategy_preview",
      "pricingStrategy": {
        "margin": 0.15,
        "minProfit": 20
      },
      "strategyNotes": "Na execução, usar schema/base_price do sistema para recalcular taxa ML real e respeitar custom_price quando existir."
    },
    {
      "produtoId": "a52a2ce4-6e95-4772-9c8a-571f99dd71ed",
      "sku": "VTK013752",
      "nome": "Terminal Direção 225mm Lado Direito Hilux Sw4 Gi 95 A 01",
      "fornecedor": "SHOPPECAS",
      "dsliteFornecedorId": "103",
      "custo": 46.61,
      "estoque": 100,
      "mlFee": 0.15,
      "mlShipping": 0,
      "customPrice": null,
      "suggestedPricePreview": 82.23,
      "priceSource": "pricing_strategy_preview",
      "pricingStrategy": {
        "margin": 0.15,
        "minProfit": 20
      },
      "strategyNotes": "Na execução, usar schema/base_price do sistema para recalcular taxa ML real e respeitar custom_price quando existir."
    },
    {
      "produtoId": "f3b28804-80e2-41f0-965c-64bce53315ef",
      "sku": "VTK013793",
      "nome": "Terminal Direção Lado Esquerdo Doblo Adventure 1.8 Após 04",
      "fornecedor": "SHOPPECAS",
      "dsliteFornecedorId": "103",
      "custo": 46.69,
      "estoque": 100,
      "mlFee": 0.15,
      "mlShipping": 0,
      "customPrice": null,
      "suggestedPricePreview": 82.33,
      "priceSource": "pricing_strategy_preview",
      "pricingStrategy": {
        "margin": 0.15,
        "minProfit": 20
      },
      "strategyNotes": "Na execução, usar schema/base_price do sistema para recalcular taxa ML real e respeitar custom_price quando existir."
    },
    {
      "produtoId": "3c584f11-940a-4049-9943-66f67a9b51c1",
      "sku": "VTK013794",
      "nome": "Terminal Direção Lado Direito Doblo Adventure 1.8 Após 04",
      "fornecedor": "SHOPPECAS",
      "dsliteFornecedorId": "103",
      "custo": 46.69,
      "estoque": 100,
      "mlFee": 0.15,
      "mlShipping": 0,
      "customPrice": null,
      "suggestedPricePreview": 82.33,
      "priceSource": "pricing_strategy_preview",
      "pricingStrategy": {
        "margin": 0.15,
        "minProfit": 20
      },
      "strategyNotes": "Na execução, usar schema/base_price do sistema para recalcular taxa ML real e respeitar custom_price quando existir."
    },
    {
      "produtoId": "64160c01-a7ec-4795-a454-6594f0f89d77",
      "sku": "VTK013812",
      "nome": "Terminal Direção Esquerdo Fiat Strada Idea Palio Weekend",
      "fornecedor": "SHOPPECAS",
      "dsliteFornecedorId": "103",
      "custo": 46.69,
      "estoque": 100,
      "mlFee": 0.15,
      "mlShipping": 0,
      "customPrice": null,
      "suggestedPricePreview": 82.33,
      "priceSource": "pricing_strategy_preview",
      "pricingStrategy": {
        "margin": 0.15,
        "minProfit": 20
      },
      "strategyNotes": "Na execução, usar schema/base_price do sistema para recalcular taxa ML real e respeitar custom_price quando existir."
    },
    {
      "produtoId": "c8a24bc1-d1c0-4eed-bc42-86c1c8983bb3",
      "sku": "VTK013813",
      "nome": "Terminal Direção Lado Direito Fiat Strada Idea Palio Weekend",
      "fornecedor": "SHOPPECAS",
      "dsliteFornecedorId": "103",
      "custo": 46.69,
      "estoque": 100,
      "mlFee": 0.15,
      "mlShipping": 0,
      "customPrice": null,
      "suggestedPricePreview": 82.33,
      "priceSource": "pricing_strategy_preview",
      "pricingStrategy": {
        "margin": 0.15,
        "minProfit": 20
      },
      "strategyNotes": "Na execução, usar schema/base_price do sistema para recalcular taxa ML real e respeitar custom_price quando existir."
    },
    {
      "produtoId": "5b3ac313-0c7b-4dd6-b3a5-4240479fd1b0",
      "sku": "VTK013400",
      "nome": "Maçaneta Tampa Caçamba Ford F1000 93 A 98 (preta)",
      "fornecedor": "SHOPPECAS",
      "dsliteFornecedorId": "103",
      "custo": 46.73,
      "estoque": 100,
      "mlFee": 0.15,
      "mlShipping": 0,
      "customPrice": null,
      "suggestedPricePreview": 82.38,
      "priceSource": "pricing_strategy_preview",
      "pricingStrategy": {
        "margin": 0.15,
        "minProfit": 20
      },
      "strategyNotes": "Na execução, usar schema/base_price do sistema para recalcular taxa ML real e respeitar custom_price quando existir."
    }
  ]
}