{
  "batchNumber": 3,
  "batchId": "ml-create-003",
  "strategy": "safe_small_batch",
  "executionHints": {
    "delayMs": 1500,
    "listingType": "gold_pro",
    "useSchemaBasePrice": true,
    "applyPricingStrategyAtRuntime": true,
    "stopIfFailureRateOver": 0.5
  },
  "items": [
    {
      "produtoId": "1a7cdbfa-ab62-413e-b202-a4689a37dab4",
      "sku": "VTK011602",
      "nome": "Chave Golf Passat Brasileiro",
      "fornecedor": "SHOPPECAS",
      "dsliteFornecedorId": "103",
      "custo": 6.71,
      "estoque": 100,
      "mlFee": 0.15,
      "mlShipping": 0,
      "customPrice": null,
      "suggestedPricePreview": 32.98,
      "priceSource": "pricing_strategy_preview",
      "pricingStrategy": {
        "margin": 0.15,
        "minProfit": 20
      },
      "strategyNotes": "Na execução, usar schema/base_price do sistema para recalcular taxa ML real e respeitar custom_price quando existir."
    },
    {
      "produtoId": "2ad68635-e803-4a5e-8451-18b874adf213",
      "sku": "VTK011513",
      "nome": "Aro Alavanca Câmbio Gol Parati Saveiro G3 Cromado",
      "fornecedor": "SHOPPECAS",
      "dsliteFornecedorId": "103",
      "custo": 6.78,
      "estoque": 100,
      "mlFee": 0.15,
      "mlShipping": 0,
      "customPrice": null,
      "suggestedPricePreview": 33.06,
      "priceSource": "pricing_strategy_preview",
      "pricingStrategy": {
        "margin": 0.15,
        "minProfit": 20
      },
      "strategyNotes": "Na execução, usar schema/base_price do sistema para recalcular taxa ML real e respeitar custom_price quando existir."
    },
    {
      "produtoId": "8c61bee4-2d53-4f06-b27c-16c431380761",
      "sku": "VTK011514",
      "nome": "Aro Alavanca Câmbio Gol Parati Saveiro G3 Cromado Até 2005",
      "fornecedor": "SHOPPECAS",
      "dsliteFornecedorId": "103",
      "custo": 6.78,
      "estoque": 100,
      "mlFee": 0.15,
      "mlShipping": 0,
      "customPrice": null,
      "suggestedPricePreview": 33.06,
      "priceSource": "pricing_strategy_preview",
      "pricingStrategy": {
        "margin": 0.15,
        "minProfit": 20
      },
      "strategyNotes": "Na execução, usar schema/base_price do sistema para recalcular taxa ML real e respeitar custom_price quando existir."
    },
    {
      "produtoId": "b09c6178-1b4c-45d5-97c1-8826e4dd647c",
      "sku": "VTK011130",
      "nome": "Maçaneta Int Porta Dian/tras Esq Parati Gol Saveiro Cinza",
      "fornecedor": "SHOPPECAS",
      "dsliteFornecedorId": "103",
      "custo": 6.8,
      "estoque": 100,
      "mlFee": 0.15,
      "mlShipping": 0,
      "customPrice": 33.09,
      "suggestedPricePreview": 33.09,
      "priceSource": "custom_price",
      "pricingStrategy": {
        "margin": 0.15,
        "minProfit": 20
      },
      "strategyNotes": "Na execução, usar schema/base_price do sistema para recalcular taxa ML real e respeitar custom_price quando existir."
    },
    {
      "produtoId": "55896457-7010-4f5d-88c2-2ca9cc0d493d",
      "sku": "VTK011131",
      "nome": "Maçaneta Interna Direita Diant Tras Parati Gol Saveiro G2 G3",
      "fornecedor": "SHOPPECAS",
      "dsliteFornecedorId": "103",
      "custo": 6.8,
      "estoque": 100,
      "mlFee": 0.15,
      "mlShipping": 0,
      "customPrice": null,
      "suggestedPricePreview": 33.09,
      "priceSource": "pricing_strategy_preview",
      "pricingStrategy": {
        "margin": 0.15,
        "minProfit": 20
      },
      "strategyNotes": "Na execução, usar schema/base_price do sistema para recalcular taxa ML real e respeitar custom_price quando existir."
    },
    {
      "produtoId": "3150ae88-18d9-4004-b856-c56b0763586d",
      "sku": "VTK011952",
      "nome": "Cabo Abertura Do Capô Gol E Gol Special Parati Saveiro 94/02",
      "fornecedor": "SHOPPECAS",
      "dsliteFornecedorId": "103",
      "custo": 6.82,
      "estoque": 100,
      "mlFee": 0.15,
      "mlShipping": 0,
      "customPrice": null,
      "suggestedPricePreview": 33.11,
      "priceSource": "pricing_strategy_preview",
      "pricingStrategy": {
        "margin": 0.15,
        "minProfit": 20
      },
      "strategyNotes": "Na execução, usar schema/base_price do sistema para recalcular taxa ML real e respeitar custom_price quando existir."
    },
    {
      "produtoId": "56281c34-ee2e-4913-b2f0-7a81abca2a25",
      "sku": "VTK011560",
      "nome": "Manivela Reguladora Vidro Vw Constellation",
      "fornecedor": "SHOPPECAS",
      "dsliteFornecedorId": "103",
      "custo": 6.86,
      "estoque": 100,
      "mlFee": 0.15,
      "mlShipping": 0,
      "customPrice": null,
      "suggestedPricePreview": 33.16,
      "priceSource": "pricing_strategy_preview",
      "pricingStrategy": {
        "margin": 0.15,
        "minProfit": 20
      },
      "strategyNotes": "Na execução, usar schema/base_price do sistema para recalcular taxa ML real e respeitar custom_price quando existir."
    },
    {
      "produtoId": "30196929-ff0c-4240-9dfa-b816661c9c7d",
      "sku": "VTK013150",
      "nome": "Cabo Acionamento Fechad Pta Tras Dir Crossfox Fox Spacefox",
      "fornecedor": "SHOPPECAS",
      "dsliteFornecedorId": "103",
      "custo": 6.9,
      "estoque": 100,
      "mlFee": 0.15,
      "mlShipping": 0,
      "customPrice": null,
      "suggestedPricePreview": 33.21,
      "priceSource": "pricing_strategy_preview",
      "pricingStrategy": {
        "margin": 0.15,
        "minProfit": 20
      },
      "strategyNotes": "Na execução, usar schema/base_price do sistema para recalcular taxa ML real e respeitar custom_price quando existir."
    },
    {
      "produtoId": "c09e0068-b6f4-4a27-bda8-000e35197978",
      "sku": "VTK013151",
      "nome": "Cabo Acionamento Fech Porta Tras Esq Crossfox Fox Spacefox",
      "fornecedor": "SHOPPECAS",
      "dsliteFornecedorId": "103",
      "custo": 6.9,
      "estoque": 100,
      "mlFee": 0.15,
      "mlShipping": 0,
      "customPrice": null,
      "suggestedPricePreview": 33.21,
      "priceSource": "pricing_strategy_preview",
      "pricingStrategy": {
        "margin": 0.15,
        "minProfit": 20
      },
      "strategyNotes": "Na execução, usar schema/base_price do sistema para recalcular taxa ML real e respeitar custom_price quando existir."
    },
    {
      "produtoId": "542b685a-e0c7-4edc-b4a9-7b7221f7c26c",
      "sku": "VTK011743",
      "nome": "Cabo Acionamento Fechadura Porta Diant Dir Gol G2 G3",
      "fornecedor": "SHOPPECAS",
      "dsliteFornecedorId": "103",
      "custo": 7.01,
      "estoque": 100,
      "mlFee": 0.15,
      "mlShipping": 0,
      "customPrice": null,
      "suggestedPricePreview": 33.35,
      "priceSource": "pricing_strategy_preview",
      "pricingStrategy": {
        "margin": 0.15,
        "minProfit": 20
      },
      "strategyNotes": "Na execução, usar schema/base_price do sistema para recalcular taxa ML real e respeitar custom_price quando existir."
    },
    {
      "produtoId": "a37ae160-291c-4677-a069-064540221548",
      "sku": "VTK011744",
      "nome": "Cabo Acionamento Fechadura Porta Diant Esq Gol G2 G3",
      "fornecedor": "SHOPPECAS",
      "dsliteFornecedorId": "103",
      "custo": 7.01,
      "estoque": 100,
      "mlFee": 0.15,
      "mlShipping": 0,
      "customPrice": null,
      "suggestedPricePreview": 33.35,
      "priceSource": "pricing_strategy_preview",
      "pricingStrategy": {
        "margin": 0.15,
        "minProfit": 20
      },
      "strategyNotes": "Na execução, usar schema/base_price do sistema para recalcular taxa ML real e respeitar custom_price quando existir."
    },
    {
      "produtoId": "772afcfa-9121-4af9-bbe6-aeb6223a5b6b",
      "sku": "VTK011534",
      "nome": "Cabo Acionamento Fechadura Porta Dian Esq Gol Parati Saveiro",
      "fornecedor": "SHOPPECAS",
      "dsliteFornecedorId": "103",
      "custo": 7.05,
      "estoque": 100,
      "mlFee": 0.15,
      "mlShipping": 0,
      "customPrice": null,
      "suggestedPricePreview": 33.4,
      "priceSource": "pricing_strategy_preview",
      "pricingStrategy": {
        "margin": 0.15,
        "minProfit": 20
      },
      "strategyNotes": "Na execução, usar schema/base_price do sistema para recalcular taxa ML real e respeitar custom_price quando existir."
    },
    {
      "produtoId": "7fef2afb-cd4a-4923-850a-fc19e0a012f1",
      "sku": "VTK011535",
      "nome": "Cabo Acionamento Fechadura Porta Dian Dir Gol Parati Saveiro",
      "fornecedor": "SHOPPECAS",
      "dsliteFornecedorId": "103",
      "custo": 7.05,
      "estoque": 100,
      "mlFee": 0.15,
      "mlShipping": 0,
      "customPrice": null,
      "suggestedPricePreview": 33.4,
      "priceSource": "pricing_strategy_preview",
      "pricingStrategy": {
        "margin": 0.15,
        "minProfit": 20
      },
      "strategyNotes": "Na execução, usar schema/base_price do sistema para recalcular taxa ML real e respeitar custom_price quando existir."
    },
    {
      "produtoId": "f1ea984d-98c3-4e46-b3b9-015695d0e104",
      "sku": "VTK013638",
      "nome": "Cj Mac Ext Diant/tras Ford Fiesta Amazon 02a14 D/e",
      "fornecedor": "SHOPPECAS",
      "dsliteFornecedorId": "103",
      "custo": 7.07,
      "estoque": 100,
      "mlFee": 0.15,
      "mlShipping": 0,
      "customPrice": null,
      "suggestedPricePreview": 33.42,
      "priceSource": "pricing_strategy_preview",
      "pricingStrategy": {
        "margin": 0.15,
        "minProfit": 20
      },
      "strategyNotes": "Na execução, usar schema/base_price do sistema para recalcular taxa ML real e respeitar custom_price quando existir."
    },
    {
      "produtoId": "c515175e-8221-4379-be81-e942f1c42c06",
      "sku": "VTK013859",
      "nome": "Pino E Bucha Conexao Cb Tramb Volvo Cam 76a84",
      "fornecedor": "SHOPPECAS",
      "dsliteFornecedorId": "103",
      "custo": 7.16,
      "estoque": 100,
      "mlFee": 0.15,
      "mlShipping": 0,
      "customPrice": null,
      "suggestedPricePreview": 33.53,
      "priceSource": "pricing_strategy_preview",
      "pricingStrategy": {
        "margin": 0.15,
        "minProfit": 20
      },
      "strategyNotes": "Na execução, usar schema/base_price do sistema para recalcular taxa ML real e respeitar custom_price quando existir."
    },
    {
      "produtoId": "2311fe74-b269-4901-aee8-b13b7c33df57",
      "sku": "VTK013149",
      "nome": "Cabo Acionamento Fech Porta Diant Esq Crossfox Fox Spacefox",
      "fornecedor": "SHOPPECAS",
      "dsliteFornecedorId": "103",
      "custo": 7.17,
      "estoque": 100,
      "mlFee": 0.15,
      "mlShipping": 0,
      "customPrice": 33.54,
      "suggestedPricePreview": 33.54,
      "priceSource": "custom_price",
      "pricingStrategy": {
        "margin": 0.15,
        "minProfit": 20
      },
      "strategyNotes": "Na execução, usar schema/base_price do sistema para recalcular taxa ML real e respeitar custom_price quando existir."
    },
    {
      "produtoId": "bdc33d73-76d7-476f-961b-c8c09efeb3f5",
      "sku": "VTK011429",
      "nome": "Grampo Desliz Trilho Banco Vw Gol 94a16",
      "fornecedor": "SHOPPECAS",
      "dsliteFornecedorId": "103",
      "custo": 7.18,
      "estoque": 100,
      "mlFee": 0.15,
      "mlShipping": 0,
      "customPrice": 33.56,
      "suggestedPricePreview": 33.56,
      "priceSource": "custom_price",
      "pricingStrategy": {
        "margin": 0.15,
        "minProfit": 20
      },
      "strategyNotes": "Na execução, usar schema/base_price do sistema para recalcular taxa ML real e respeitar custom_price quando existir."
    },
    {
      "produtoId": "e51b88f4-a4e1-476c-a1df-03c2bf85c4be",
      "sku": "VTK011601",
      "nome": "Cabo Acionamento Fechadura Pta Tras Esq Gol Parati Saveiro",
      "fornecedor": "SHOPPECAS",
      "dsliteFornecedorId": "103",
      "custo": 7.21,
      "estoque": 100,
      "mlFee": 0.15,
      "mlShipping": 0,
      "customPrice": null,
      "suggestedPricePreview": 33.59,
      "priceSource": "pricing_strategy_preview",
      "pricingStrategy": {
        "margin": 0.15,
        "minProfit": 20
      },
      "strategyNotes": "Na execução, usar schema/base_price do sistema para recalcular taxa ML real e respeitar custom_price quando existir."
    },
    {
      "produtoId": "259f926c-2ca2-4239-834c-5a7ee24fdee6",
      "sku": "VTK013158",
      "nome": "Cabo Acionamento Fechadura Porta Tras Dir Gol Parati Saveiro",
      "fornecedor": "SHOPPECAS",
      "dsliteFornecedorId": "103",
      "custo": 7.21,
      "estoque": 100,
      "mlFee": 0.15,
      "mlShipping": 0,
      "customPrice": 33.59,
      "suggestedPricePreview": 33.59,
      "priceSource": "custom_price",
      "pricingStrategy": {
        "margin": 0.15,
        "minProfit": 20
      },
      "strategyNotes": "Na execução, usar schema/base_price do sistema para recalcular taxa ML real e respeitar custom_price quando existir."
    },
    {
      "produtoId": "83c1c8c7-35ad-4faf-8cd5-a876427db6bb",
      "sku": "VTK013565",
      "nome": "Cabo Acionamento Fechadura Porta Diant Dir Ecosport 03 A 12",
      "fornecedor": "SHOPPECAS",
      "dsliteFornecedorId": "103",
      "custo": 7.31,
      "estoque": 100,
      "mlFee": 0.15,
      "mlShipping": 0,
      "customPrice": null,
      "suggestedPricePreview": 33.72,
      "priceSource": "pricing_strategy_preview",
      "pricingStrategy": {
        "margin": 0.15,
        "minProfit": 20
      },
      "strategyNotes": "Na execução, usar schema/base_price do sistema para recalcular taxa ML real e respeitar custom_price quando existir."
    },
    {
      "produtoId": "d4f77add-69f9-427c-8887-6f8a93f4b185",
      "sku": "VTK013493",
      "nome": "Puxador Liberação Frio Ford F1000 F2000 F4000 Amarelo",
      "fornecedor": "SHOPPECAS",
      "dsliteFornecedorId": "103",
      "custo": 7.33,
      "estoque": 100,
      "mlFee": 0.15,
      "mlShipping": 0,
      "customPrice": null,
      "suggestedPricePreview": 33.74,
      "priceSource": "pricing_strategy_preview",
      "pricingStrategy": {
        "margin": 0.15,
        "minProfit": 20
      },
      "strategyNotes": "Na execução, usar schema/base_price do sistema para recalcular taxa ML real e respeitar custom_price quando existir."
    },
    {
      "produtoId": "ab429957-fc6f-4f85-86e6-e4161d2498cb",
      "sku": "VTK011825",
      "nome": "Chapa Embreagem Guia Vw Fusca 59 A 96",
      "fornecedor": "SHOPPECAS",
      "dsliteFornecedorId": "103",
      "custo": 7.39,
      "estoque": 100,
      "mlFee": 0.15,
      "mlShipping": 0,
      "customPrice": null,
      "suggestedPricePreview": 33.81,
      "priceSource": "pricing_strategy_preview",
      "pricingStrategy": {
        "margin": 0.15,
        "minProfit": 20
      },
      "strategyNotes": "Na execução, usar schema/base_price do sistema para recalcular taxa ML real e respeitar custom_price quando existir."
    },
    {
      "produtoId": "321e4455-4fa3-431f-a17f-929cd862b018",
      "sku": "VTK012357",
      "nome": "5 Cr 1620 Elgin 01 Cartela",
      "fornecedor": "BKR1",
      "dsliteFornecedorId": "108",
      "custo": 7.5,
      "estoque": 19,
      "mlFee": 0.15,
      "mlShipping": 0,
      "customPrice": null,
      "suggestedPricePreview": 33.95,
      "priceSource": "pricing_strategy_preview",
      "pricingStrategy": {
        "margin": 0.15,
        "minProfit": 20
      },
      "strategyNotes": "Na execução, usar schema/base_price do sistema para recalcular taxa ML real e respeitar custom_price quando existir."
    },
    {
      "produtoId": "d37f68ee-93a5-4075-9f2f-839a51a85954",
      "sku": "VTK013509",
      "nome": "Cabo Acionamento Fechadura Porta Diant Ld Ecosport Fiesta",
      "fornecedor": "SHOPPECAS",
      "dsliteFornecedorId": "103",
      "custo": 7.56,
      "estoque": 100,
      "mlFee": 0.15,
      "mlShipping": 0,
      "customPrice": null,
      "suggestedPricePreview": 34.02,
      "priceSource": "pricing_strategy_preview",
      "pricingStrategy": {
        "margin": 0.15,
        "minProfit": 20
      },
      "strategyNotes": "Na execução, usar schema/base_price do sistema para recalcular taxa ML real e respeitar custom_price quando existir."
    },
    {
      "produtoId": "e19193f4-34b9-4530-9a9d-51cbf0d84510",
      "sku": "VTK013510",
      "nome": "Cabo Acionamento Fechadura Porta Diant Le Ecosport Fiesta",
      "fornecedor": "SHOPPECAS",
      "dsliteFornecedorId": "103",
      "custo": 7.56,
      "estoque": 100,
      "mlFee": 0.15,
      "mlShipping": 0,
      "customPrice": null,
      "suggestedPricePreview": 34.02,
      "priceSource": "pricing_strategy_preview",
      "pricingStrategy": {
        "margin": 0.15,
        "minProfit": 20
      },
      "strategyNotes": "Na execução, usar schema/base_price do sistema para recalcular taxa ML real e respeitar custom_price quando existir."
    }
  ]
}